{
  "error": null,
  "ga_best_fitness": 84,
  "ga_best_fitness_by_gen": [
    84,
    84,
    84,
    84,
    84,
    84,
    84,
    84,
    84,
    84,
    84
  ],
  "ga_final_sat_count": 1599,
  "ga_final_unknown_count": 2505,
  "ga_final_unsat_count": 681,
  "ga_generations_completed": 10,
  "ga_individuals_evaluated": 2750,
  "ga_path": "scripts/test3/outputs/sensitivity/phi2/G2/seed3/2025-12-28_20_01_36.439734",
  "ga_sec": 483.6148500442505,
  "ga_target_sats": 1000,
  "j48_runs": [
    {
      "arff_exists": true,
      "arff_path": "scripts/test3/outputs/sensitivity/phi2/G2/seed3/2025-12-28_20_01_36.439734/dataset_qty_2025-12-28_20_01_36.439734_per100.arff",
      "class_balance": 0.43954968184043075,
      "class_counts": {
        "FALSE": 898,
        "TRUE": 1145
      },
      "false_count": 898,
      "j48_out_path": "scripts/test3/outputs/sensitivity/phi2/G2/seed3/2025-12-28_20_01_36.439734/J48-data-100.out",
      "missing_values": 0,
      "num_attributes": 18,
      "num_features": 17,
      "num_instances": 2043,
      "qty": 1.0,
      "root_split": "NUM3 <= 1.999804",
      "tree_depth": 1,
      "tree_leaves": 9,
      "tree_nodes": 19,
      "true_count": 1145,
      "weka_correct_pct": 100.0,
      "weka_incorrect_pct": 0.0,
      "weka_kappa": 1.0,
      "weka_num_leaves": 3,
      "weka_time_build_sec": 0.02,
      "weka_time_test_sec": 0.01,
      "weka_total_instances": 2043,
      "weka_tree_size": 5
    },
    {
      "arff_exists": true,
      "arff_path": "scripts/test3/outputs/sensitivity/phi2/G2/seed3/2025-12-28_20_01_36.439734/dataset_qty_2025-12-28_20_01_36.439734_per025.arff",
      "class_balance": 0.4346978557504873,
      "class_counts": {
        "FALSE": 223,
        "TRUE": 290
      },
      "false_count": 223,
      "j48_out_path": "scripts/test3/outputs/sensitivity/phi2/G2/seed3/2025-12-28_20_01_36.439734/J48-data-25.out",
      "missing_values": 0,
      "num_attributes": 18,
      "num_features": 17,
      "num_instances": 513,
      "qty": 0.25,
      "root_split": "NUM3 <= 1.984877",
      "tree_depth": 1,
      "tree_leaves": 9,
      "tree_nodes": 19,
      "true_count": 290,
      "weka_correct_pct": 100.0,
      "weka_incorrect_pct": 0.0,
      "weka_kappa": 1.0,
      "weka_num_leaves": 3,
      "weka_time_build_sec": 0.02,
      "weka_time_test_sec": 0.01,
      "weka_total_instances": 513,
      "weka_tree_size": 5
    },
    {
      "arff_exists": true,
      "arff_path": "scripts/test3/outputs/sensitivity/phi2/G2/seed3/2025-12-28_20_01_36.439734/dataset_qty_2025-12-28_20_01_36.439734_per020.arff",
      "class_balance": 0.43795620437956206,
      "class_counts": {
        "FALSE": 180,
        "TRUE": 231
      },
      "false_count": 180,
      "j48_out_path": "scripts/test3/outputs/sensitivity/phi2/G2/seed3/2025-12-28_20_01_36.439734/J48-data-20.out",
      "missing_values": 0,
      "num_attributes": 18,
      "num_features": 17,
      "num_instances": 411,
      "qty": 0.2,
      "root_split": "NUM3 <= 1.967002",
      "tree_depth": 1,
      "tree_leaves": 9,
      "tree_nodes": 19,
      "true_count": 231,
      "weka_correct_pct": 100.0,
      "weka_incorrect_pct": 0.0,
      "weka_kappa": 1.0,
      "weka_num_leaves": 3,
      "weka_time_build_sec": 0.02,
      "weka_time_test_sec": 0.0,
      "weka_total_instances": 411,
      "weka_tree_size": 5
    },
    {
      "arff_exists": true,
      "arff_path": "scripts/test3/outputs/sensitivity/phi2/G2/seed3/2025-12-28_20_01_36.439734/dataset_qty_2025-12-28_20_01_36.439734_per015.arff",
      "class_balance": 0.44660194174757284,
      "class_counts": {
        "FALSE": 138,
        "TRUE": 171
      },
      "false_count": 138,
      "j48_out_path": "scripts/test3/outputs/sensitivity/phi2/G2/seed3/2025-12-28_20_01_36.439734/J48-data-15.out",
      "missing_values": 0,
      "num_attributes": 18,
      "num_features": 17,
      "num_instances": 309,
      "qty": 0.15,
      "root_split": "NUM3 <= 1.967002",
      "tree_depth": 1,
      "tree_leaves": 9,
      "tree_nodes": 19,
      "true_count": 171,
      "weka_correct_pct": 100.0,
      "weka_incorrect_pct": 0.0,
      "weka_kappa": 1.0,
      "weka_num_leaves": 3,
      "weka_time_build_sec": 0.02,
      "weka_time_test_sec": 0.0,
      "weka_total_instances": 309,
      "weka_tree_size": 5
    },
    {
      "arff_exists": true,
      "arff_path": "scripts/test3/outputs/sensitivity/phi2/G2/seed3/2025-12-28_20_01_36.439734/dataset_qty_2025-12-28_20_01_36.439734_per010.arff",
      "class_balance": 0.4444444444444444,
      "class_counts": {
        "FALSE": 92,
        "TRUE": 115
      },
      "false_count": 92,
      "j48_out_path": "scripts/test3/outputs/sensitivity/phi2/G2/seed3/2025-12-28_20_01_36.439734/J48-data-10.out",
      "missing_values": 0,
      "num_attributes": 18,
      "num_features": 17,
      "num_instances": 207,
      "qty": 0.1,
      "root_split": "NUM3 <= 1.967002",
      "tree_depth": 1,
      "tree_leaves": 9,
      "tree_nodes": 19,
      "true_count": 115,
      "weka_correct_pct": 100.0,
      "weka_incorrect_pct": 0.0,
      "weka_kappa": 1.0,
      "weka_num_leaves": 3,
      "weka_time_build_sec": 0.01,
      "weka_time_test_sec": 0.0,
      "weka_total_instances": 207,
      "weka_tree_size": 5
    }
  ],
  "max_generations": 10,
  "output_dir": "/opt/ga-hls/scripts/test3/outputs/sensitivity/phi2/G2/seed3",
  "population_size": 250,
  "requirement_file": "scripts/test3/configs/property_trace/property_phi2_cutin.py",
  "requirement_sha256": "7bcce829c3fa62ba8ed427013d5f4ebbb96ba437e37b390d21351d7333c2fbb3",
  "runtime_sec": 484.723375082016,
  "seed": 3,
  "success": true,
  "traces_file": "na",
  "traces_sha256": null
}