{
  "error": null,
  "ga_best_fitness": 100,
  "ga_best_fitness_by_gen": [
    95,
    100,
    100,
    100,
    100,
    100,
    100,
    95,
    100,
    95,
    100
  ],
  "ga_final_sat_count": 244,
  "ga_final_unknown_count": 1691,
  "ga_final_unsat_count": 1290,
  "ga_generations_completed": 10,
  "ga_individuals_evaluated": 2750,
  "ga_path": "outputs/sensitivity/phi3/O2/seed0/2025-12-24_08_24_27.314754",
  "ga_sec": 598.0380318164825,
  "ga_target_sats": 1000,
  "j48_runs": [
    {
      "arff_exists": true,
      "arff_path": "outputs/sensitivity/phi3/O2/seed0/2025-12-24_08_24_27.314754/dataset_qty_2025-12-24_08_24_27.314754_per100.arff",
      "class_balance": 0.4248633879781421,
      "class_counts": {
        "FALSE": 421,
        "TRUE": 311
      },
      "false_count": 421,
      "j48_out_path": "outputs/sensitivity/phi3/O2/seed0/2025-12-24_08_24_27.314754/J48-data-100.out",
      "missing_values": 0,
      "num_attributes": 41,
      "num_features": 40,
      "num_instances": 732,
      "qty": 1.0,
      "root_split": "NUM3 <= 2.799387: TRUE (311.0)",
      "tree_depth": 1,
      "tree_leaves": 8,
      "tree_nodes": 18,
      "true_count": 311,
      "weka_correct_pct": 100.0,
      "weka_incorrect_pct": 0.0,
      "weka_kappa": 1.0,
      "weka_num_leaves": 2,
      "weka_time_build_sec": 0.02,
      "weka_time_test_sec": 0.01,
      "weka_total_instances": 732,
      "weka_tree_size": 3
    },
    {
      "arff_exists": true,
      "arff_path": "outputs/sensitivity/phi3/O2/seed0/2025-12-24_08_24_27.314754/dataset_qty_2025-12-24_08_24_27.314754_per025.arff",
      "class_balance": 0.4207650273224044,
      "class_counts": {
        "FALSE": 106,
        "TRUE": 77
      },
      "false_count": 106,
      "j48_out_path": "outputs/sensitivity/phi3/O2/seed0/2025-12-24_08_24_27.314754/J48-data-25.out",
      "missing_values": 0,
      "num_attributes": 41,
      "num_features": 40,
      "num_instances": 183,
      "qty": 0.25,
      "root_split": "NUM3 <= 2.799387: TRUE (77.0)",
      "tree_depth": 1,
      "tree_leaves": 8,
      "tree_nodes": 18,
      "true_count": 77,
      "weka_correct_pct": 100.0,
      "weka_incorrect_pct": 0.0,
      "weka_kappa": 1.0,
      "weka_num_leaves": 2,
      "weka_time_build_sec": 0.01,
      "weka_time_test_sec": 0.0,
      "weka_total_instances": 183,
      "weka_tree_size": 3
    },
    {
      "arff_exists": true,
      "arff_path": "outputs/sensitivity/phi3/O2/seed0/2025-12-24_08_24_27.314754/dataset_qty_2025-12-24_08_24_27.314754_per020.arff",
      "class_balance": 0.41496598639455784,
      "class_counts": {
        "FALSE": 86,
        "TRUE": 61
      },
      "false_count": 86,
      "j48_out_path": "outputs/sensitivity/phi3/O2/seed0/2025-12-24_08_24_27.314754/J48-data-20.out",
      "missing_values": 0,
      "num_attributes": 41,
      "num_features": 40,
      "num_instances": 147,
      "qty": 0.2,
      "root_split": "NUM3 <= 2.799387: TRUE (61.0)",
      "tree_depth": 1,
      "tree_leaves": 8,
      "tree_nodes": 18,
      "true_count": 61,
      "weka_correct_pct": 100.0,
      "weka_incorrect_pct": 0.0,
      "weka_kappa": 1.0,
      "weka_num_leaves": 2,
      "weka_time_build_sec": 0.01,
      "weka_time_test_sec": 0.0,
      "weka_total_instances": 147,
      "weka_tree_size": 3
    },
    {
      "arff_exists": true,
      "arff_path": "outputs/sensitivity/phi3/O2/seed0/2025-12-24_08_24_27.314754/dataset_qty_2025-12-24_08_24_27.314754_per015.arff",
      "class_balance": 0.3963963963963964,
      "class_counts": {
        "FALSE": 67,
        "TRUE": 44
      },
      "false_count": 67,
      "j48_out_path": "outputs/sensitivity/phi3/O2/seed0/2025-12-24_08_24_27.314754/J48-data-15.out",
      "missing_values": 0,
      "num_attributes": 41,
      "num_features": 40,
      "num_instances": 111,
      "qty": 0.15,
      "root_split": "NUM3 <= 2.799387: TRUE (44.0)",
      "tree_depth": 1,
      "tree_leaves": 8,
      "tree_nodes": 18,
      "true_count": 44,
      "weka_correct_pct": 100.0,
      "weka_incorrect_pct": 0.0,
      "weka_kappa": 1.0,
      "weka_num_leaves": 2,
      "weka_time_build_sec": 0.01,
      "weka_time_test_sec": 0.0,
      "weka_total_instances": 111,
      "weka_tree_size": 3
    },
    {
      "arff_exists": true,
      "arff_path": "outputs/sensitivity/phi3/O2/seed0/2025-12-24_08_24_27.314754/dataset_qty_2025-12-24_08_24_27.314754_per010.arff",
      "class_balance": 0.4,
      "class_counts": {
        "FALSE": 45,
        "TRUE": 30
      },
      "false_count": 45,
      "j48_out_path": "outputs/sensitivity/phi3/O2/seed0/2025-12-24_08_24_27.314754/J48-data-10.out",
      "missing_values": 0,
      "num_attributes": 41,
      "num_features": 40,
      "num_instances": 75,
      "qty": 0.1,
      "root_split": "NUM3 <= 2.799226: TRUE (30.0)",
      "tree_depth": 1,
      "tree_leaves": 8,
      "tree_nodes": 18,
      "true_count": 30,
      "weka_correct_pct": 100.0,
      "weka_incorrect_pct": 0.0,
      "weka_kappa": 1.0,
      "weka_num_leaves": 2,
      "weka_time_build_sec": 0.01,
      "weka_time_test_sec": 0.0,
      "weka_total_instances": 75,
      "weka_tree_size": 3
    }
  ],
  "max_generations": 10,
  "output_dir": "/opt/ga-hls/outputs/sensitivity/phi3/O2/seed0",
  "population_size": 250,
  "requirement_file": "configs/sensitivity/property_trace/property_phi3_retry.py",
  "requirement_sha256": "89e86c8b64172d6134055285f658a3a2fbdc9447972b7f7935c87c16f51a8c0f",
  "runtime_sec": 599.3786385059357,
  "seed": 0,
  "success": true,
  "traces_file": "na",
  "traces_sha256": null
}